pyl2h/__init__.py
pyl2h/__main__.py
pyl2h/cloud_client.py
pyl2h/const.py
pyl2h/udp.py
pyl2h-0.2.1.dist-info/METADATA
pyl2h-0.2.1.dist-info/WHEEL
pyl2h-0.2.1.dist-info/entry_points.txt
pyl2h-0.2.1.dist-info/top_level.txt
pyl2h-0.2.1.dist-info/RECORD
