Metadata-Version: 2.1
Name: pyl2h
Version: 0.2.1
Summary: Python library for controlling Link2Home devices
Author: oxygen0211
Project-URL: Homepage, https://github.com/oxygen0211/pyl2h
Keywords: iot,smarthome,link2home,l2h
Classifier: License :: OSI Approved :: MIT License
Classifier: Programming Language :: Python
Classifier: Programming Language :: Python :: 3
Requires-Python: >=3.7
Requires-Dist: feedparser >=5.2.0
Requires-Dist: html2text
Requires-Dist: pycryptodome
Requires-Dist: requests
Requires-Dist: tomli ; python_version < "3.11"
Provides-Extra: dev
Requires-Dist: black ; extra == 'dev'
Requires-Dist: bumpver ; extra == 'dev'
Requires-Dist: isort ; extra == 'dev'
Requires-Dist: pip-tools ; extra == 'dev'
Requires-Dist: pytest ; extra == 'dev'
